setup.py
bin/niice
bin/niice_hwinfo
bin/niiced
niice/__init__.py
niice/manage.py
niice/server.py
niice/server_configuration.py
niice/subscriber.py
niice/utils.py
niice.egg-info/PKG-INFO
niice.egg-info/SOURCES.txt
niice.egg-info/dependency_links.txt
niice.egg-info/requires.txt
niice.egg-info/top_level.txt
niice/tasks/__init__.py
niice/tasks/basetask.py
niice/tasks/median_15_seconds.py
niice/tasks/sanitizer.py
niice_client/__init__.py
niice_client/basic_configuration.py
niice_client/client.py
niice_client/client_configuration.py
niice_client/event.py