Metadata-Version: 1.0
Name: niice
Version: 0.0.1.0
Summary: In-house metrics collection engine.
Home-page: https://github.com/Revel-Systems/niice
Author: mkorenkov
Author-email: mkorenkov@gmail.com
License: Proprietary, All rights reserved.
Platform: UNKNOWN
